setup.py
python/gegede/__init__.py
python/gegede/builder.py
python/gegede/configuration.py
python/gegede/construct.py
python/gegede/dot.py
python/gegede/interp.py
python/gegede/iter.py
python/gegede/main.py
python/gegede/util.py
python/gegede/validation.py
python/gegede.egg-info/PKG-INFO
python/gegede.egg-info/SOURCES.txt
python/gegede.egg-info/dependency_links.txt
python/gegede.egg-info/entry_points.txt
python/gegede.egg-info/requires.txt
python/gegede.egg-info/top_level.txt
python/gegede/examples/__init__.py
python/gegede/examples/builders.py
python/gegede/examples/lar.py
python/gegede/examples/simple.py
python/gegede/export/__init__.py
python/gegede/export/ggdjson.py
python/gegede/export/pod.py
python/gegede/export/root.py
python/gegede/export/scenegraph.py
python/gegede/export/gdml/__init__.py
python/gegede/schema/__init__.py
python/gegede/schema/tools.py
python/gegede/schema/types.py