Metadata-Version: 2.1
Name: gegede
Version: 0.8
Summary: General Geometry Description
Home-page: http://github.com/brettviren/gegede
Author: Brett Viren
Author-email: brett.viren@gmail.com
License: GPLv2
